tdxlite/__about__.py
tdxlite/__init__.py
tdxlite/utils.py
tdxlite/client/__init__.py
tdxlite/client/base_client.py
tdxlite/client/tdx_client.py
tdxlite/constants/__init__.py
tdxlite/constants/board.py
tdxlite/constants/exchange.py
tdxlite/constants/msg_type.py
tdxlite/constants/protocol_spec.py
tdxlite/models/__init__.py
tdxlite/models/resp_view_data.py
tdxlite/models/send_view_data.py
tdxlite/parse/__init__.py
tdxlite/parse/base_parse.py
tdxlite/parse/parse_beat_heart.py
tdxlite/parse/parse_short_market.py
tdxlite/req/__init__.py
tdxlite/req/base_req.py
tdxlite/req/beat_heart_req.py
tdxlite/req/short_market_req.py
tdxlite-1.0.0.dist-info/METADATA
tdxlite-1.0.0.dist-info/WHEEL
tdxlite-1.0.0.dist-info/licenses/LICENSE.txt
tdxlite-1.0.0.dist-info/RECORD
