Metadata-Version: 2.4
Name: tdxlite
Version: 1.0.0
Summary: A lightweight TDX protocol parser and client library
Project-URL: Homepage, https://github.com/jett2025ab/tdxlite
Project-URL: Repository, https://github.com/jett2025ab/tdxlite
Project-URL: Documentation, https://github.com/jett2025ab/tdxlite#readme
Author-email: jett2025ab <jett2025ab@outlook.com>
License-Expression: MIT
License-File: LICENSE.txt
Keywords: finance,quant,tdx,trading
Classifier: License :: OSI Approved :: MIT License
Classifier: Programming Language :: Python
Classifier: Programming Language :: Python :: 3.10
Classifier: Programming Language :: Python :: 3.11
Classifier: Programming Language :: Python :: 3.12
Requires-Python: <3.13,>=3.10
Requires-Dist: bitstring
Provides-Extra: test
Requires-Dist: pytest; extra == 'test'
Requires-Dist: pytest-cov; extra == 'test'
